criptam/__init__.py
criptam/__main__.py
criptam/decrypt.py
criptam/device.py
criptam/ipsw.py
criptam/manifest.py
criptam/utils.py
criptam-1.0b3.dist-info/entry_points.txt
criptam-1.0b3.dist-info/LICENSE
criptam-1.0b3.dist-info/WHEEL
criptam-1.0b3.dist-info/METADATA
criptam-1.0b3.dist-info/RECORD
